CMakeLists.txt
LICENSE
MANIFEST.in
README.md
pyproject.toml
setup.cfg
setup.py
versioneer.py
ext/eigen/.git
ext/eigen/.gitignore
ext/eigen/.hgeol
ext/eigen/CMakeLists.txt
ext/eigen/COPYING.BSD
ext/eigen/COPYING.GPL
ext/eigen/COPYING.LGPL
ext/eigen/COPYING.MINPACK
ext/eigen/COPYING.MPL2
ext/eigen/COPYING.README
ext/eigen/CTestConfig.cmake
ext/eigen/CTestCustom.cmake.in
ext/eigen/INSTALL
ext/eigen/README.md
ext/eigen/eigen3.pc.in
ext/eigen/signature_of_eigen3_matrix_library
ext/eigen/Eigen/CMakeLists.txt
ext/eigen/Eigen/Cholesky
ext/eigen/Eigen/CholmodSupport
ext/eigen/Eigen/Core
ext/eigen/Eigen/Dense
ext/eigen/Eigen/Eigen
ext/eigen/Eigen/Eigenvalues
ext/eigen/Eigen/Geometry
ext/eigen/Eigen/Householder
ext/eigen/Eigen/IterativeLinearSolvers
ext/eigen/Eigen/Jacobi
ext/eigen/Eigen/LU
ext/eigen/Eigen/MetisSupport
ext/eigen/Eigen/OrderingMethods
ext/eigen/Eigen/PaStiXSupport
ext/eigen/Eigen/PardisoSupport
ext/eigen/Eigen/QR
ext/eigen/Eigen/QtAlignedMalloc
ext/eigen/Eigen/SPQRSupport
ext/eigen/Eigen/SVD
ext/eigen/Eigen/Sparse
ext/eigen/Eigen/SparseCholesky
ext/eigen/Eigen/SparseCore
ext/eigen/Eigen/SparseLU
ext/eigen/Eigen/SparseQR
ext/eigen/Eigen/StdDeque
ext/eigen/Eigen/StdList
ext/eigen/Eigen/StdVector
ext/eigen/Eigen/SuperLUSupport
ext/eigen/Eigen/UmfPackSupport
ext/eigen/Eigen/src/Cholesky/LDLT.h
ext/eigen/Eigen/src/Cholesky/LLT.h
ext/eigen/Eigen/src/Cholesky/LLT_LAPACKE.h
ext/eigen/Eigen/src/CholmodSupport/CholmodSupport.h
ext/eigen/Eigen/src/Core/Array.h
ext/eigen/Eigen/src/Core/ArrayBase.h
ext/eigen/Eigen/src/Core/ArrayWrapper.h
ext/eigen/Eigen/src/Core/Assign.h
ext/eigen/Eigen/src/Core/AssignEvaluator.h
ext/eigen/Eigen/src/Core/Assign_MKL.h
ext/eigen/Eigen/src/Core/BandMatrix.h
ext/eigen/Eigen/src/Core/Block.h
ext/eigen/Eigen/src/Core/BooleanRedux.h
ext/eigen/Eigen/src/Core/CommaInitializer.h
ext/eigen/Eigen/src/Core/ConditionEstimator.h
ext/eigen/Eigen/src/Core/CoreEvaluators.h
ext/eigen/Eigen/src/Core/CoreIterators.h
ext/eigen/Eigen/src/Core/CwiseBinaryOp.h
psvWave.egg-info/PKG-INFO
psvWave.egg-info/SOURCES.txt
psvWave.egg-info/dependency_links.txt
psvWave.egg-info/not-zip-safe
psvWave.egg-info/requires.txt
psvWave.egg-info/top_level.txt
