Metadata-Version: 2.1
Name: psvWave
Version: 0.2.1
Summary: P-SV wave propagation in 2D for FWI
Home-page: https://github.com/larsgeb/forward-virieux
Author: Lars Gebraad
Author-email: lars.gebraad@erdw.ethz.ch
License: UNKNOWN
Platform: UNKNOWN
Classifier: Development Status :: 3 - Alpha
Classifier: Programming Language :: Python :: 3.7
Classifier: License :: OSI Approved :: BSD License
Classifier: Operating System :: OS Independent
Requires-Python: >=3.7
Provides-Extra: dev
License-File: LICENSE
